Metadata-Version: 2.1
Name: stack_fetcher_bakircius
Version: 0.5.0
Summary: A small fetcher for Stack Exchange API
Author-email: bakircius <burakbakirci@gmail.com>
Project-URL: Homepage, https://github.com/bakircius/stack-exchange-fetcher
Project-URL: Issues, https://github.com/bakircius/stack-exchange-fetcher/issues
Classifier: Programming Language :: Python :: 3
Classifier: License :: OSI Approved :: MIT License
Classifier: Operating System :: OS Independent
Requires-Python: >=3.8
License-File: LICENSE
Requires-Dist: requests
Requires-Dist: pandas
Requires-Dist: numpy
